kqcircuits/__init__.py
kqcircuits/defaults.py
kqcircuits/klayout_view.py
kqcircuits/layer_cluster.py
kqcircuits/pya_resolver.py
kqcircuits/run.py
kqcircuits/chips/__init__.py
kqcircuits/chips/airbridge_crossings.py
kqcircuits/chips/airbridge_dc_test.py
kqcircuits/chips/chip.py
kqcircuits/chips/crossing_twoface.py
kqcircuits/chips/daisy_woven.py
kqcircuits/chips/dc_test.py
kqcircuits/chips/demo.py
kqcircuits/chips/demo_twoface.py
kqcircuits/chips/empty.py
kqcircuits/chips/junction_test.py
kqcircuits/chips/junction_test2.py
kqcircuits/chips/launchers.py
kqcircuits/chips/lithography_test.py
kqcircuits/chips/lithography_test_twoface.py
kqcircuits/chips/munch_qubits.py
kqcircuits/chips/quality_factor.py
kqcircuits/chips/quality_factor_twoface.py
kqcircuits/chips/sample_holder_test.py
kqcircuits/chips/shaping.py
kqcircuits/chips/simple.py
kqcircuits/chips/single_xmons.py
kqcircuits/chips/stripes.py
kqcircuits/chips/tsv_test.py
kqcircuits/chips/xmons_direct_coupling.py
kqcircuits/elements/__init__.py
kqcircuits/elements/airbridge_connection.py
kqcircuits/elements/capacitive_x_coupler.py
kqcircuits/elements/chip_frame.py
kqcircuits/elements/circular_capacitor.py
kqcircuits/elements/daisy_woven.oas
kqcircuits/elements/element.py
kqcircuits/elements/finger_capacitor_square.py
kqcircuits/elements/finger_capacitor_taper.py
kqcircuits/elements/hanger_resonator.py
kqcircuits/elements/launcher.py
kqcircuits/elements/launcher_dc.py
kqcircuits/elements/meander.py
kqcircuits/elements/quarter_wave_cpw_resonator.py
kqcircuits/elements/smooth_capacitor.py
kqcircuits/elements/spiral_capacitor.py
kqcircuits/elements/spiral_resonator_polygon.py
kqcircuits/elements/waveguide_composite.py
kqcircuits/elements/waveguide_coplanar.py
kqcircuits/elements/waveguide_coplanar_curved.py
kqcircuits/elements/waveguide_coplanar_splitter.py
kqcircuits/elements/waveguide_coplanar_straight.py
kqcircuits/elements/waveguide_coplanar_taper.py
kqcircuits/elements/airbridges/__init__.py
kqcircuits-4.9.7.dist-info/METADATA
kqcircuits-4.9.7.dist-info/WHEEL
kqcircuits-4.9.7.dist-info/entry_points.txt
kqcircuits-4.9.7.dist-info/top_level.txt
kqcircuits-4.9.7.dist-info/RECORD
