Metadata-Version: 2.4
Name: kqcircuits
Version: 4.9.7
Summary: KQCircuits is a KLayout/Python-based superconducting quantum circuit library developed by IQM.
Author-email: IQM Finland Oy <kqcircuits@meetiqm.com>
License: GPL-3.0
Project-URL: Homepage, https://iqm-finland.github.io/KQCircuits/
Classifier: Development Status :: 4 - Beta
Classifier: Programming Language :: Python :: 3 :: Only
Classifier: Topic :: Scientific/Engineering :: Physics
Classifier: Intended Audience :: Science/Research
Requires-Python: >=3.10
Requires-Dist: klayout
Requires-Dist: numpy==2.2.6
Requires-Dist: scipy==1.15.3
Requires-Dist: tqdm
Requires-Dist: versiontag
Requires-Dist: networkx
Requires-Dist: matplotlib
Provides-Extra: dev
Requires-Dist: pytest; extra == "dev"
Requires-Dist: pytest-cov; extra == "dev"
Requires-Dist: pytest-xdist; extra == "dev"
Requires-Dist: tox; extra == "dev"
Requires-Dist: pylint; extra == "dev"
Requires-Dist: black; extra == "dev"
Requires-Dist: pytest-mock; extra == "dev"
Requires-Dist: sphinx; extra == "dev"
Requires-Dist: sphinx-rtd-theme; extra == "dev"
Provides-Extra: sim
Requires-Dist: gmsh; extra == "sim"
Requires-Dist: pandas; extra == "sim"
Requires-Dist: scikit-rf==0.32.0; extra == "sim"
Requires-Dist: qutip; extra == "sim"
